cbr/__init__.py
cbr/cbr.py
python_cbr-0.2.0.dist-info/LICENSE
python_cbr-0.2.0.dist-info/METADATA
python_cbr-0.2.0.dist-info/WHEEL
python_cbr-0.2.0.dist-info/top_level.txt
python_cbr-0.2.0.dist-info/RECORD
