Metadata-Version: 2.1
Name: python-cbr
Version: 0.2.0
Summary: Read the official exchange rates data from cbr.ru
Home-page: https://github.com/grunichev/cbr
Author: Alexey Grunichev
Author-email: grunichev@gmail.com
License: MIT
Platform: UNKNOWN
Classifier: License :: OSI Approved :: MIT License
Classifier: Programming Language :: Python :: 3
Classifier: Programming Language :: Python :: 3.7
